Metadata-Version: 2.1
Name: odoo-addon-stock_picking_type_shipping_policy
Version: 17.0.1.0.0.3
Requires-Python: >=3.10
Requires-Dist: odoo>=17.0a,<17.1dev
Summary: Define different shipping policies according to picking type
Home-page: https://github.com/OCA/wms
License: AGPL-3
Author: Camptocamp, Odoo Community Association (OCA)
Author-email: support@odoo-community.org
Classifier: Programming Language :: Python
Classifier: Framework :: Odoo
Classifier: Framework :: Odoo :: 17.0
Classifier: License :: OSI Approved :: GNU Affero General Public License v3
Classifier: Development Status :: 5 - Production/Stable
